pychoosealicense/_licenses/0bsd.txt
pychoosealicense/_licenses/__init__.py
pychoosealicense/_licenses/afl-3.0.txt
pychoosealicense/_licenses/agpl-3.0.txt
pychoosealicense/_licenses/apache-2.0.txt
pychoosealicense/_licenses/artistic-2.0.txt
pychoosealicense/_licenses/bsd-2-clause.txt
pychoosealicense/_licenses/bsd-3-clause-clear.txt
pychoosealicense/_licenses/bsd-3-clause.txt
pychoosealicense/_licenses/bsd-4-clause.txt
pychoosealicense/_licenses/bsl-1.0.txt
pychoosealicense/_licenses/cc-by-4.0.txt
pychoosealicense/_licenses/cc-by-sa-4.0.txt
pychoosealicense/_licenses/cc0-1.0.txt
pychoosealicense/_licenses/cecill-2.1.txt
pychoosealicense/_licenses/cern-ohl-p-2.0.txt
pychoosealicense/_licenses/cern-ohl-s-2.0.txt
pychoosealicense/_licenses/cern-ohl-w-2.0.txt
pychoosealicense/_licenses/ecl-2.0.txt
pychoosealicense/_licenses/epl-1.0.txt
pychoosealicense/_licenses/epl-2.0.txt
pychoosealicense/_licenses/eupl-1.1.txt
pychoosealicense/_licenses/eupl-1.2.txt
pychoosealicense/_licenses/gfdl-1.3.txt
pychoosealicense/_licenses/gpl-2.0.txt
pychoosealicense/_licenses/gpl-3.0.txt
pychoosealicense/_licenses/isc.txt
pychoosealicense/_licenses/lgpl-2.1.txt
pychoosealicense/_licenses/lgpl-3.0.txt
pychoosealicense/_licenses/lppl-1.3c.txt
pychoosealicense/_licenses/mit-0.txt
pychoosealicense/_licenses/mit.txt
pychoosealicense/_licenses/mpl-2.0.txt
pychoosealicense/_licenses/ms-pl.txt
pychoosealicense/_licenses/ms-rl.txt
pychoosealicense/_licenses/mulanpsl-2.0.txt
pychoosealicense/_licenses/ncsa.txt
pychoosealicense/_licenses/odbl-1.0.txt
pychoosealicense/_licenses/ofl-1.1.txt
pychoosealicense/_licenses/osl-3.0.txt
pychoosealicense/_licenses/postgresql.txt
pychoosealicense/_licenses/unlicense.txt
pychoosealicense/_licenses/upl-1.0.txt
pychoosealicense/_licenses/vim.txt
pychoosealicense/_licenses/wtfpl.txt
pychoosealicense/_licenses/zlib.txt
pychoosealicense/rules/__init__.py
pychoosealicense/rules/rules.yml
pychoosealicense/__init__.py
pychoosealicense/__main__.py
pychoosealicense/_cli.py
pychoosealicense-2023.11.20.dist-info/LICENSE
pychoosealicense-2023.11.20.dist-info/METADATA
pychoosealicense-2023.11.20.dist-info/WHEEL
pychoosealicense-2023.11.20.dist-info/entry_points.txt
pychoosealicense-2023.11.20.dist-info/RECORD
