Metadata-Version: 2.1
Name: pychoosealicense
Version: 2023.11.20
Summary: Provides license metadata from choosealicense.com
Author-email: Dominic Davis-Foster <dominic@davis-foster.co.uk>
License: MIT
Keywords: license
Home-page: https://github.com/repo-helper/PyChooseALicense
Project-URL: Issue Tracker, https://github.com/repo-helper/PyChooseALicense/issues
Project-URL: Source Code, https://github.com/repo-helper/PyChooseALicense
Project-URL: Documentation, https://pychoosealicense.readthedocs.io/en/latest
Platform: Windows
Platform: macOS
Platform: Linux
Classifier: Development Status :: 4 - Beta
Classifier: Intended Audience :: Developers
Classifier: License :: OSI Approved :: MIT License
Classifier: Operating System :: OS Independent
Classifier: Programming Language :: Python
Classifier: Programming Language :: Python :: 3 :: Only
Classifier: Programming Language :: Python :: 3.6
Classifier: Programming Language :: Python :: 3.7
Classifier: Programming Language :: Python :: 3.8
Classifier: Programming Language :: Python :: 3.9
Classifier: Programming Language :: Python :: 3.10
Classifier: Programming Language :: Python :: 3.11
Classifier: Programming Language :: Python :: 3.12
Classifier: Programming Language :: Python :: Implementation :: CPython
Classifier: Programming Language :: Python :: Implementation :: PyPy
Classifier: Topic :: Software Development :: Libraries :: Python Modules
Classifier: Typing :: Typed
Requires-Python: >=3.6
Requires-Dist: domdf-python-tools>=3.2.0
Requires-Dist: python-frontmatter>=1.0.0
Requires-Dist: pyyaml>=5.4.1
Requires-Dist: typing-extensions>=3.10.0.0
Requires-Dist: click>=8.0.1; extra == 'cli'
Requires-Dist: consolekit>=1.2.3; extra == 'cli'
Requires-Dist: click>=8.0.1; extra == 'all'
Requires-Dist: consolekit>=1.2.3; extra == 'all'
Provides-Extra: cli
Provides-Extra: all
